{
  "annotations": {
    "list": [
      {
        "builtIn": 1,
        "datasource": "-- Grafana --",
        "enable": true,
        "hide": true,
        "iconColor": "rgba(0, 211, 255, 1)",
        "name": "Annotations & Alerts",
        "type": "dashboard"
      }
    ]
  },
  "editable": true,
  "gnetId": null,
  "graphTooltip": 0,
  "id": 4,
  "links": [],
  "panels": [
    {
      "aliasColors": {},
      "bars": false,
      "dashLength": 10,
      "dashes": false,
      "datasource": "PostgreSQL",
      "fieldConfig": {
        "defaults": {
          "custom": {}
        },
        "overrides": []
      },
      "fill": 1,
      "fillGradient": 0,
      "gridPos": {
        "h": 8,
        "w": 24,
        "x": 0,
        "y": 0
      },
      "hiddenSeries": false,
      "id": 2,
      "legend": {
        "alignAsTable": false,
        "avg": false,
        "current": false,
        "max": false,
        "min": false,
        "rightSide": true,
        "show": true,
        "total": false,
        "values": false
      },
      "lines": true,
      "linewidth": 1,
      "nullPointMode": "null",
      "options": {
        "dataLinks": []
      },
      "percentage": false,
      "pointradius": 2,
      "points": false,
      "renderer": "flot",
      "seriesOverrides": [],
      "spaceLength": 10,
      "stack": false,
      "steppedLine": false,
      "targets": [
        {
          "format": "time_series",
          "group": [],
          "metricColumn": "name",
          "rawQuery": false,
          "rawSql": "SELECT\n  heart_rate_ts AS \"time\",\n  name AS metric,\n  heart_rate\nFROM ecg\nORDER BY 1,2",
          "refId": "A",
          "select": [
            [
              {
                "params": [
                  "heart_rate"
                ],
                "type": "column"
              }
            ]
          ],
          "table": "ecg",
          "timeColumn": "heart_rate_ts",
          "timeColumnType": "float8",
          "where": []
        }
      ],
      "thresholds": [],
      "timeFrom": null,
      "timeRegions": [],
      "timeShift": null,
      "title": "Heart Rate",
      "tooltip": {
        "shared": true,
        "sort": 0,
        "value_type": "individual"
      },
      "type": "graph",
      "xaxis": {
        "buckets": null,
        "mode": "time",
        "name": null,
        "show": true,
        "values": []
      },
      "yaxes": [
        {
          "format": "short",
          "label": null,
          "logBase": 1,
          "max": null,
          "min": null,
          "show": true
        },
        {
          "format": "short",
          "label": null,
          "logBase": 1,
          "max": null,
          "min": null,
          "show": true
        }
      ],
      "yaxis": {
        "align": false,
        "alignLevel": null
      }
    },
    {
      "datasource": "PostgreSQL",
      "fieldConfig": {
        "defaults": {
          "custom": {
            "align": "center"
          },
          "mappings": [],
          "thresholds": {
            "mode": "absolute",
            "steps": [
              {
                "color": "green",
                "value": null
              },
              {
                "color": "red",
                "value": 80
              }
            ]
          }
        },
        "overrides": []
      },
      "gridPos": {
        "h": 7,
        "w": 24,
        "x": 0,
        "y": 8
      },
      "id": 4,
      "options": {
        "showHeader": true
      },
      "pluginVersion": "7.0.0",
      "targets": [
        {
          "format": "table",
          "group": [],
          "metricColumn": "none",
          "rawQuery": true,
          "rawSql": "SELECT\n  name AS \"time\",\n  heart_rate as heart_rate,\n  heart_rate_ts as heart_rate_ts\nFROM ecg\nORDER BY 1",
          "refId": "A",
          "select": [
            [
              {
                "params": [
                  "heart_rate"
                ],
                "type": "column"
              }
            ]
          ],
          "table": "ecg",
          "timeColumn": "heart_rate",
          "timeColumnType": "float8",
          "where": [
            {
              "name": "$__unixEpochFilter",
              "params": [],
              "type": "macro"
            }
          ]
        }
      ],
      "timeFrom": null,
      "timeShift": null,
      "title": "Heart Rate Table",
      "type": "table"
    }
  ],
  "refresh": false,
  "schemaVersion": 25,
  "style": "dark",
  "tags": [],
  "templating": {
    "list": []
  },
  "time": {
    "from": "1969-12-31T23:59:59.996Z",
    "to": "1970-01-01T00:00:00.013Z"
  },
  "timepicker": {},
  "timezone": "",
  "title": "Patients - ECG",
  "uid": "P4i2drigz",
  "version": 1
}